CHANGES.txt
LICENSE.txt
MANIFEST.in
README.txt
setup.py
js/__init__.py
js.wysihtml5.egg-info/PKG-INFO
js.wysihtml5.egg-info/SOURCES.txt
js.wysihtml5.egg-info/dependency_links.txt
js.wysihtml5.egg-info/entry_points.txt
js.wysihtml5.egg-info/namespace_packages.txt
js.wysihtml5.egg-info/not-zip-safe
js.wysihtml5.egg-info/requires.txt
js.wysihtml5.egg-info/top_level.txt
js/wysihtml5/__init__.py
js/wysihtml5/test_wysihtml5.txt
js/wysihtml5/resources/js/wysihtml5-0.3.0.js
js/wysihtml5/resources/js/wysihtml5-0.3.0.min.js
js/wysihtml5/resources/parser_rules/advanced.js
js/wysihtml5/resources/parser_rules/simple.js