Metadata-Version: 1.0
Name: js.wysihtml5
Version: 0.3.0
Summary: Fanstatic packaging of wysihtml5
Home-page: https://github.com/teixas/js.wysihtml5
Author: Fanstatic Developers
Author-email: fanstatic@googlegroups.com
License: BSD
Platform: UNKNOWN
